Wviz/__init__.py
Wviz/core.py
Wviz/install.py
Wviz/_internal/__init__.py
Wviz/_internal/helpers.py
Wviz/_internal/implementation.py
wviz-0.1.1.dist-info/METADATA
wviz-0.1.1.dist-info/WHEEL
wviz-0.1.1.dist-info/top_level.txt
wviz-0.1.1.dist-info/RECORD
