Metadata-Version: 2.4
Name: Wviz
Version: 0.1.1
Requires-Python: >=3.8
Requires-Dist: opencv-python<5.0.0,>=4.11.0
Requires-Dist: numpy<3.0.0,>=2.0.2
Requires-Dist: pandas<3.0.0,>=2.2.2
Requires-Dist: pytesseract<0.4.0,>=0.3.13
Requires-Dist: easyocr<2.0.0,>=1.7.0
Dynamic: requires-python
